NOTICE
log_rate_limit/__init__.py
log_rate_limit/log_rate_limit.py
log_rate_limit/streams.py
log_rate_limit-1.4.2.dist-info/LICENSE
log_rate_limit-1.4.2.dist-info/METADATA
log_rate_limit-1.4.2.dist-info/WHEEL
log_rate_limit-1.4.2.dist-info/RECORD
