Metadata-Version: 2.1
Name: log-rate-limit
Version: 1.4.2
Summary: Limit excessive log output with Python's standard logging framework.
Home-page: https://github.com/samuller/log-rate-limit/blob/main/README.md
Keywords: logging,log,limit,rate
Author: Simon Muller
Author-email: samullers@gmail.com
Requires-Python: >=3.8.1,<4.0.0
Classifier: Development Status :: 5 - Production/Stable
Classifier: Intended Audience :: Developers
Classifier: License :: OSI Approved :: Apache Software License
Classifier: Natural Language :: English
Classifier: Programming Language :: Python :: 3
Classifier: Programming Language :: Python :: 3.9
Classifier: Programming Language :: Python :: 3.10
Classifier: Programming Language :: Python :: 3.11
Classifier: Programming Language :: Python :: 3 :: Only
Classifier: Topic :: Software Development :: Libraries
Classifier: Topic :: System :: Logging
Provides-Extra: redis
Requires-Dist: redis (==4.6.0) ; extra == "redis"
Project-URL: Changelog, https://github.com/samuller/log-rate-limit/blob/main/CHANGELOG.md
Project-URL: Repository, https://github.com/samuller/log-rate-limit
